<?xml version="1.0" encoding="windows-1252"?>
<XMI xmi.version="1.1" xmlns:UML="omg.org/UML1.3" timestamp="2021-12-29 23:17:46">
	<XMI.header>
		<XMI.documentation>
			<XMI.exporter>Enterprise Architect</XMI.exporter>
			<XMI.exporterVersion>2.5</XMI.exporterVersion>
			<XMI.exporterID>1559</XMI.exporterID>
		</XMI.documentation>
	</XMI.header>
	<XMI.content>
		<UML:Model name="EA Model" xmi.id="MX_EAID_71E7E50B_00B3_41c4_8F29_D9DD21BE474C">
			<UML:Namespace.ownedElement>
				<UML:Class name="EARootClass" xmi.id="EAID_11111111_5487_4080_A7F4_41526CB0AA00" isRoot="true" isLeaf="false" isAbstract="false"/>
				<UML:Package name="TEN-T veg" xmi.id="EAPK_71E7E50B_00B3_41c4_8F29_D9DD21BE474C" isRoot="false" isLeaf="false" isAbstract="false" visibility="public">
					<UML:ModelElement.taggedValue>
						<UML:TaggedValue tag="documentation" value="Veg som inngår i det trans-europeiske vegnettet (Trans European Network - Transport). I regi av EU. Definert og er vedtatt i vedtak nr 1692/96/EF. Referert i HB R511 (269) - Sikkerhetsforvaltning av vegtunneler. Brukes også til CEDR rapportering"/>
						<UML:TaggedValue tag="parent" value="EAPK_393D4B7A_A14F_4466_B0AF_06C59CB157F8"/>
						<UML:TaggedValue tag="created" value="2011-08-26 15:45:57"/>
						<UML:TaggedValue tag="modified" value="2017-05-26 09:10:01"/>
						<UML:TaggedValue tag="iscontrolled" value="TRUE"/>
						<UML:TaggedValue tag="xmlpath" value="C:\DATA\GitHub\vegvesen\NVDB-Datakatalogen\UML\XMI\Vegobjekttyper\826.xml"/>
						<UML:TaggedValue tag="lastloaddate" value="2017-03-05 22:36:16"/>
						<UML:TaggedValue tag="lastsavedate" value="2021-12-29 23:17:46"/>
						<UML:TaggedValue tag="isprotected" value="FALSE"/>
						<UML:TaggedValue tag="usedtd" value="FALSE"/>
						<UML:TaggedValue tag="xmiver" value="Enterprise Architect XMI/UML 1.3"/>
						<UML:TaggedValue tag="logxml" value="FALSE"/>
						<UML:TaggedValue tag="tpos" value="288"/>
						<UML:TaggedValue tag="packageFlags" value="Recurse=1;"/>
						<UML:TaggedValue tag="batchsave" value="1"/>
						<UML:TaggedValue tag="batchload" value="1"/>
						<UML:TaggedValue tag="phase" value="1.0"/>
						<UML:TaggedValue tag="status" value="Implemented"/>
						<UML:TaggedValue tag="author" value="knjetl"/>
						<UML:TaggedValue tag="alias" value="826"/>
						<UML:TaggedValue tag="complexity" value="1"/>
						<UML:TaggedValue tag="ea_stype" value="Public"/>
						<UML:TaggedValue tag="tpos" value="282"/>
						<UML:TaggedValue tag="gentype" value="Java"/>
					</UML:ModelElement.taggedValue>
					<UML:Namespace.ownedElement>
						<UML:Class name="TEN-T veg" xmi.id="EAID_11EC4E2B_B58C_46c8_BECB_B180738A39C0" visibility="public" namespace="EAPK_71E7E50B_00B3_41c4_8F29_D9DD21BE474C" isRoot="false" isLeaf="false" isAbstract="false" isActive="false">
							<UML:ModelElement.stereotype>
								<UML:Stereotype name="Vegobjekttype"/>
							</UML:ModelElement.stereotype>
							<UML:ModelElement.taggedValue>
								<UML:TaggedValue tag="documentation" value="Veg som inngår i det trans-europeiske vegnettet (Trans European Network - Transport). I regi av EU. Definert og er vedtatt i vedtak nr 1692/96/EF. Referert i HB R511 (269) - Sikkerhetsforvaltning av vegtunneler. Brukes også til CEDR rapportering"/>
								<UML:TaggedValue tag="isSpecification" value="false"/>
								<UML:TaggedValue tag="ea_stype" value="Class"/>
								<UML:TaggedValue tag="ea_ntype" value="0"/>
								<UML:TaggedValue tag="version" value="2.27"/>
								<UML:TaggedValue tag="package" value="EAPK_71E7E50B_00B3_41c4_8F29_D9DD21BE474C"/>
								<UML:TaggedValue tag="date_created" value="2011-08-26 15:45:57"/>
								<UML:TaggedValue tag="date_modified" value="2021-12-29 17:24:12"/>
								<UML:TaggedValue tag="tagged" value="0"/>
								<UML:TaggedValue tag="package_name" value="TEN-T veg"/>
								<UML:TaggedValue tag="phase" value="1.0"/>
								<UML:TaggedValue tag="alias" value="826"/>
								<UML:TaggedValue tag="author" value="Dakat"/>
								<UML:TaggedValue tag="complexity" value="1"/>
								<UML:TaggedValue tag="status" value="Implemented"/>
								<UML:TaggedValue tag="stereotype" value="Vegobjekttype"/>
								<UML:TaggedValue tag="tpos" value="1"/>
								<UML:TaggedValue tag="ea_localid" value="29200"/>
								<UML:TaggedValue tag="ea_eleType" value="element"/>
								<UML:TaggedValue tag="style" value="BackColor=-1;BorderColor=-1;BorderWidth=-1;FontColor=-1;VSwimLanes=1;HSwimLanes=1;BorderStyle=0;"/>
								<UML:TaggedValue tag="$ea_xref_property" value="$XREFPROP=$XID={088369D4-A0C8-4d1b-8551-F9D69CE089B9}$XID;$NAM=Stereotypes$NAM;$TYP=element property$TYP;$VIS=Public$VIS;$PAR=0$PAR;$DES=@STEREO;Name=Vegobjekttype;GUID={BB16F6AC-B50E-485f-AADA-7E99A4B6A412};@ENDSTEREO;$DES;$CLT={11EC4E2B-B58C-46c8-BECB-B180738A39C0}$CLT;$SUP=&lt;none&gt;$SUP;$ENDXREF;"/>
							</UML:ModelElement.taggedValue>
							<UML:Classifier.feature>
								<UML:Attribute name="CEDR Strekningsnavn" changeable="none" visibility="public" ownerScope="instance" targetScope="instance">
									<UML:Attribute.initialValue>
										<UML:Expression/>
									</UML:Attribute.initialValue>
									<UML:StructuralFeature.type>
										<UML:Classifier xmi.idref="EAID_968D5712_8BD7_4710_BA39_A16179F74C46"/>
									</UML:StructuralFeature.type>
									<UML:ModelElement.taggedValue>
										<UML:TaggedValue tag="description" value="Gir navn på strekning. Følger CEDR-regelverk for navning."/>
										<UML:TaggedValue tag="type" value="Tekst"/>
										<UML:TaggedValue tag="derived" value="0"/>
										<UML:TaggedValue tag="containment" value="Not Specified"/>
										<UML:TaggedValue tag="length" value="80"/>
										<UML:TaggedValue tag="ordered" value="0"/>
										<UML:TaggedValue tag="precision" value="0"/>
										<UML:TaggedValue tag="scale" value="0"/>
										<UML:TaggedValue tag="static" value="0"/>
										<UML:TaggedValue tag="collection" value="false"/>
										<UML:TaggedValue tag="position" value="1"/>
										<UML:TaggedValue tag="lowerBound" value="1"/>
										<UML:TaggedValue tag="upperBound" value="1"/>
										<UML:TaggedValue tag="duplicates" value="0"/>
										<UML:TaggedValue tag="ea_guid" value="{05822823-AA09-4518-8B71-9DAAA8569EC5}"/>
										<UML:TaggedValue tag="ea_localid" value="139096"/>
										<UML:TaggedValue tag="style" value="10945"/>
										<UML:TaggedValue tag="$ea_xref_property" value="$XREFPROP=$XID={7573EAFD-7EFE-451f-8949-6B8811D7F1DE}$XID;$NAM=CustomProperties$NAM;$TYP=attribute property$TYP;$VIS=Public$VIS;$PAR=0$PAR;$DES=@PROP=@NAME=isID@ENDNAME;@TYPE=Boolean@ENDTYPE;@VALU=0@ENDVALU;@PRMT=@ENDPRMT;@ENDPROP;$DES;$CLT={05822823-AA09-4518-8B71-9DAAA8569EC5}$CLT;$SUP=&lt;none&gt;$SUP;$ENDXREF;"/>
										<UML:TaggedValue tag="ID_EGENSKAPSTYPE" value="10945" xmi.id="EAID_46CC57F9_7483_44d9_BF8D_B7FFCDC81E84"/>
										<UML:TaggedValue tag="NAVN_EGENSKAPSTYPE" value="CEDR Strekningsnavn" xmi.id="EAID_0C1A45A7_08FB_4b5f_8AE6_6CE5381E08EF"/>
										<UML:TaggedValue tag="KORTN_EGENSKAPSTYPE" value="strekNvn" xmi.id="EAID_44BF2DA1_B3C5_492e_9870_E2EC652E7065"/>
										<UML:TaggedValue tag="TOTAL_FELTLENGDE" value="80" xmi.id="EAID_886EF7C5_92CD_48bd_860B_5C82305FF552"/>
										<UML:TaggedValue tag="SOSINVDB_navn" value="CEDRStrekningsnavn_10945" xmi.id="EAID_7284A68B_76CF_4af9_A760_53B9345A3038"/>
										<UML:TaggedValue tag="SOSI_navn" value="CEDRStrekningsnavn" xmi.id="EAID_F275A91C_8383_4ec9_8FF2_2F2FB1BB2A9C"/>
										<UML:TaggedValue tag="Viktighet" value="Påkrevd ved nyregistrering" xmi.id="EAID_5A4E4410_F487_4000_80BA_6B44846D121C"/>
									</UML:ModelElement.taggedValue>
								</UML:Attribute>
								<UML:Attribute name="CEDR Lenkekode" changeable="none" visibility="public" ownerScope="instance" targetScope="instance">
									<UML:Attribute.initialValue>
										<UML:Expression/>
									</UML:Attribute.initialValue>
									<UML:StructuralFeature.type>
										<UML:Classifier xmi.idref="EAID_968D5712_8BD7_4710_BA39_A16179F74C46"/>
									</UML:StructuralFeature.type>
									<UML:ModelElement.taggedValue>
										<UML:TaggedValue tag="description" value="CEDR kode for hvilke funksjonell lenke (functional link) denne strekningen er en del av. Følger CEDR-regelverk for koding."/>
										<UML:TaggedValue tag="type" value="Tekst"/>
										<UML:TaggedValue tag="derived" value="0"/>
										<UML:TaggedValue tag="containment" value="Not Specified"/>
										<UML:TaggedValue tag="length" value="80"/>
										<UML:TaggedValue tag="ordered" value="0"/>
										<UML:TaggedValue tag="precision" value="0"/>
										<UML:TaggedValue tag="scale" value="0"/>
										<UML:TaggedValue tag="static" value="0"/>
										<UML:TaggedValue tag="collection" value="false"/>
										<UML:TaggedValue tag="position" value="2"/>
										<UML:TaggedValue tag="lowerBound" value="1"/>
										<UML:TaggedValue tag="upperBound" value="1"/>
										<UML:TaggedValue tag="duplicates" value="0"/>
										<UML:TaggedValue tag="ea_guid" value="{BEFA3ACC-DDB2-4334-8DF9-C589545E1665}"/>
										<UML:TaggedValue tag="ea_localid" value="139094"/>
										<UML:TaggedValue tag="style" value="11500"/>
										<UML:TaggedValue tag="$ea_xref_property" value="$XREFPROP=$XID={B1A55A7B-BAC6-4b8d-8AA2-6B2394F40E8E}$XID;$NAM=CustomProperties$NAM;$TYP=attribute property$TYP;$VIS=Public$VIS;$PAR=0$PAR;$DES=@PROP=@NAME=isID@ENDNAME;@TYPE=Boolean@ENDTYPE;@VALU=0@ENDVALU;@PRMT=@ENDPRMT;@ENDPROP;$DES;$CLT={BEFA3ACC-DDB2-4334-8DF9-C589545E1665}$CLT;$SUP=&lt;none&gt;$SUP;$ENDXREF;"/>
										<UML:TaggedValue tag="ID_EGENSKAPSTYPE" value="11500" xmi.id="EAID_67B46122_E354_475f_B53C_221D3D8239D0"/>
										<UML:TaggedValue tag="NAVN_EGENSKAPSTYPE" value="CEDR Lenkekode" xmi.id="EAID_ACB68D93_D5C0_447e_9892_C35151A53DFE"/>
										<UML:TaggedValue tag="KORTN_EGENSKAPSTYPE" value="Lenkekod" xmi.id="EAID_2B4A8C21_E0DF_480f_A39B_E8DF531895F0"/>
										<UML:TaggedValue tag="TOTAL_FELTLENGDE" value="80" xmi.id="EAID_46A0682C_120F_46bd_A6D3_B215DA514F3F"/>
										<UML:TaggedValue tag="SOSINVDB_navn" value="CEDRLenkekode_11500" xmi.id="EAID_6F25606C_80C8_40a0_8C6B_4A503459989B"/>
										<UML:TaggedValue tag="SOSI_navn" value="CEDRLenkekode" xmi.id="EAID_36D48A98_484A_4991_A4E0_61A26C419387"/>
										<UML:TaggedValue tag="Viktighet" value="Påkrevd ved nyregistrering" xmi.id="EAID_930DBAF2_08CA_420e_9379_4D6DA18581D6"/>
									</UML:ModelElement.taggedValue>
								</UML:Attribute>
								<UML:Attribute name="CEDR Strekningskode" changeable="none" visibility="public" ownerScope="instance" targetScope="instance">
									<UML:Attribute.initialValue>
										<UML:Expression/>
									</UML:Attribute.initialValue>
									<UML:StructuralFeature.type>
										<UML:Classifier xmi.idref="EAID_968D5712_8BD7_4710_BA39_A16179F74C46"/>
									</UML:StructuralFeature.type>
									<UML:ModelElement.taggedValue>
										<UML:TaggedValue tag="description" value="Kode på vegstrekningen. Følger CEDR-regelverk for koding."/>
										<UML:TaggedValue tag="type" value="Tekst"/>
										<UML:TaggedValue tag="derived" value="0"/>
										<UML:TaggedValue tag="containment" value="Not Specified"/>
										<UML:TaggedValue tag="length" value="12"/>
										<UML:TaggedValue tag="ordered" value="0"/>
										<UML:TaggedValue tag="precision" value="0"/>
										<UML:TaggedValue tag="scale" value="0"/>
										<UML:TaggedValue tag="static" value="0"/>
										<UML:TaggedValue tag="collection" value="false"/>
										<UML:TaggedValue tag="position" value="4"/>
										<UML:TaggedValue tag="lowerBound" value="1"/>
										<UML:TaggedValue tag="upperBound" value="1"/>
										<UML:TaggedValue tag="duplicates" value="0"/>
										<UML:TaggedValue tag="ea_guid" value="{B1A523A9-1BE1-44fd-B41A-FDDFDCCB9207}"/>
										<UML:TaggedValue tag="ea_localid" value="139095"/>
										<UML:TaggedValue tag="style" value="10946"/>
										<UML:TaggedValue tag="$ea_xref_property" value="$XREFPROP=$XID={FC1BFA02-50B1-4099-8AEF-416F9BD14626}$XID;$NAM=CustomProperties$NAM;$TYP=attribute property$TYP;$VIS=Public$VIS;$PAR=0$PAR;$DES=@PROP=@NAME=isID@ENDNAME;@TYPE=Boolean@ENDTYPE;@VALU=0@ENDVALU;@PRMT=@ENDPRMT;@ENDPROP;$DES;$CLT={B1A523A9-1BE1-44fd-B41A-FDDFDCCB9207}$CLT;$SUP=&lt;none&gt;$SUP;$ENDXREF;"/>
										<UML:TaggedValue tag="ID_EGENSKAPSTYPE" value="10946" xmi.id="EAID_2554230C_CCCD_4bce_BA36_A2BD5934D746"/>
										<UML:TaggedValue tag="NAVN_EGENSKAPSTYPE" value="CEDR Strekningskode" xmi.id="EAID_F935B398_8DF0_4ee3_89D7_A54811E2B4DE"/>
										<UML:TaggedValue tag="KORTN_EGENSKAPSTYPE" value="strekKod" xmi.id="EAID_F1692B59_3D76_4ba4_BA30_CF3D6042950B"/>
										<UML:TaggedValue tag="TOTAL_FELTLENGDE" value="12" xmi.id="EAID_25A8A9FF_8AC4_449b_B433_158B7221EAD2"/>
										<UML:TaggedValue tag="SOSINVDB_navn" value="CEDRStrekningskode_10946" xmi.id="EAID_5166DDF3_BBBE_44b2_8918_FCA6ADE3D428"/>
										<UML:TaggedValue tag="SOSI_navn" value="CEDRStrekningskode" xmi.id="EAID_1029C1D2_0A7A_42f7_8DA4_113CEFC8B123"/>
										<UML:TaggedValue tag="Viktighet" value="Påkrevd ved nyregistrering" xmi.id="EAID_F6378DF2_C082_4c83_8F57_569829A452C6"/>
									</UML:ModelElement.taggedValue>
								</UML:Attribute>
								<UML:Attribute name="CEDR Vegtype" changeable="none" visibility="public" ownerScope="instance" targetScope="instance">
									<UML:Attribute.initialValue>
										<UML:Expression/>
									</UML:Attribute.initialValue>
									<UML:StructuralFeature.type>
										<UML:Classifier xmi.idref="EAID_6F0E67D6_1534_467f_89B2_D454FE1774C3"/>
									</UML:StructuralFeature.type>
									<UML:ModelElement.taggedValue>
										<UML:TaggedValue tag="description" value="Angir hvilken vegtype det er tale om. Definisjoner av vegtyper i henhold til CEDR."/>
										<UML:TaggedValue tag="type" value="FlerverdiAttributt, Tekst"/>
										<UML:TaggedValue tag="derived" value="0"/>
										<UML:TaggedValue tag="containment" value="Not Specified"/>
										<UML:TaggedValue tag="length" value="20"/>
										<UML:TaggedValue tag="ordered" value="0"/>
										<UML:TaggedValue tag="precision" value="0"/>
										<UML:TaggedValue tag="scale" value="0"/>
										<UML:TaggedValue tag="static" value="0"/>
										<UML:TaggedValue tag="collection" value="false"/>
										<UML:TaggedValue tag="position" value="6"/>
										<UML:TaggedValue tag="lowerBound" value="0"/>
										<UML:TaggedValue tag="upperBound" value="1"/>
										<UML:TaggedValue tag="duplicates" value="0"/>
										<UML:TaggedValue tag="ea_guid" value="{0744F72A-6895-4c37-98FE-E430C58CE2B3}"/>
										<UML:TaggedValue tag="ea_localid" value="139097"/>
										<UML:TaggedValue tag="style" value="10947"/>
										<UML:TaggedValue tag="$ea_xref_property" value="$XREFPROP=$XID={DE3F95C8-AF50-4fba-BD6B-52EA88C8412B}$XID;$NAM=CustomProperties$NAM;$TYP=attribute property$TYP;$VIS=Public$VIS;$PAR=0$PAR;$DES=@PROP=@NAME=isID@ENDNAME;@TYPE=Boolean@ENDTYPE;@VALU=0@ENDVALU;@PRMT=@ENDPRMT;@ENDPROP;$DES;$CLT={0744F72A-6895-4c37-98FE-E430C58CE2B3}$CLT;$SUP=&lt;none&gt;$SUP;$ENDXREF;"/>
										<UML:TaggedValue tag="ID_EGENSKAPSTYPE" value="10947" xmi.id="EAID_9DE7A3AE_47D7_4889_BAC1_2FDE3F58AEAA"/>
										<UML:TaggedValue tag="NAVN_EGENSKAPSTYPE" value="CEDR Vegtype" xmi.id="EAID_886F0F75_AF33_48dd_9A8D_25482D2C70B9"/>
										<UML:TaggedValue tag="KORTN_EGENSKAPSTYPE" value="vegtype" xmi.id="EAID_0350950C_48CE_49e9_8A67_18EDC8B341FB"/>
										<UML:TaggedValue tag="TOTAL_FELTLENGDE" value="20" xmi.id="EAID_0540C5C9_5456_4d22_AA64_DFEA3FC7CA8A"/>
										<UML:TaggedValue tag="SOSINVDB_navn" value="CEDRVegtype_10947" xmi.id="EAID_BBC8424C_04D0_49c9_A916_2276E7A1B249"/>
										<UML:TaggedValue tag="SOSI_navn" value="CEDRVegtype" xmi.id="EAID_A417FA34_ABF8_48b1_95AE_609D0F21054F"/>
										<UML:TaggedValue tag="Viktighet" value="Opsjonell" xmi.id="EAID_CBD1004A_DFE7_4584_8516_6FC3E168179E"/>
									</UML:ModelElement.taggedValue>
								</UML:Attribute>
								<UML:Attribute name="CEDR ITS-nivå" changeable="none" visibility="public" ownerScope="instance" targetScope="instance">
									<UML:Attribute.initialValue>
										<UML:Expression/>
									</UML:Attribute.initialValue>
									<UML:StructuralFeature.type>
										<UML:Classifier xmi.idref="EAID_6F0E67D6_1534_467f_89B2_D454FE1774C3"/>
									</UML:StructuralFeature.type>
									<UML:ModelElement.taggedValue>
										<UML:TaggedValue tag="description" value="Angir hvilket nivå vegstrekningen ligger på i forhold til ITS-systemer/ITS-styring. De ulike nivåene er definert av CEDR."/>
										<UML:TaggedValue tag="type" value="FlerverdiAttributt, Tekst"/>
										<UML:TaggedValue tag="derived" value="0"/>
										<UML:TaggedValue tag="containment" value="Not Specified"/>
										<UML:TaggedValue tag="length" value="30"/>
										<UML:TaggedValue tag="ordered" value="0"/>
										<UML:TaggedValue tag="precision" value="0"/>
										<UML:TaggedValue tag="scale" value="0"/>
										<UML:TaggedValue tag="static" value="0"/>
										<UML:TaggedValue tag="collection" value="false"/>
										<UML:TaggedValue tag="position" value="8"/>
										<UML:TaggedValue tag="lowerBound" value="0"/>
										<UML:TaggedValue tag="upperBound" value="1"/>
										<UML:TaggedValue tag="duplicates" value="0"/>
										<UML:TaggedValue tag="ea_guid" value="{89B4EDA5-15B1-4d8f-908F-C2B96002B209}"/>
										<UML:TaggedValue tag="ea_localid" value="139093"/>
										<UML:TaggedValue tag="style" value="10948"/>
										<UML:TaggedValue tag="$ea_xref_property" value="$XREFPROP=$XID={B45DFF0D-3C28-46e3-BFC0-03244AEBBD4F}$XID;$NAM=CustomProperties$NAM;$TYP=attribute property$TYP;$VIS=Public$VIS;$PAR=0$PAR;$DES=@PROP=@NAME=isID@ENDNAME;@TYPE=Boolean@ENDTYPE;@VALU=0@ENDVALU;@PRMT=@ENDPRMT;@ENDPROP;$DES;$CLT={89B4EDA5-15B1-4d8f-908F-C2B96002B209}$CLT;$SUP=&lt;none&gt;$SUP;$ENDXREF;"/>
										<UML:TaggedValue tag="ID_EGENSKAPSTYPE" value="10948" xmi.id="EAID_1BFE520D_A9E3_4d5c_B964_DEB14BC3A873"/>
										<UML:TaggedValue tag="NAVN_EGENSKAPSTYPE" value="CEDR ITS-nivå" xmi.id="EAID_416FC6A2_5D07_491f_ACE0_204A70D89C3C"/>
										<UML:TaggedValue tag="KORTN_EGENSKAPSTYPE" value="ITSNiva" xmi.id="EAID_C81FFBBB_EABA_406e_9E2F_1935862DFF2A"/>
										<UML:TaggedValue tag="TOTAL_FELTLENGDE" value="30" xmi.id="EAID_DB15B35E_394A_4259_B467_AF09D06F09F5"/>
										<UML:TaggedValue tag="SOSINVDB_navn" value="CEDRITS-nivå_10948" xmi.id="EAID_AE6ABB41_05CE_450a_8423_0D0DA00DBA58"/>
										<UML:TaggedValue tag="SOSI_navn" value="DR_ITS_Nivå" xmi.id="EAID_A7326EFB_176D_48ed_8DBD_827CF1231D96"/>
										<UML:TaggedValue tag="Viktighet" value="Opsjonell" xmi.id="EAID_530A8A30_C769_4234_BA52_20FE0BAA4EC6"/>
									</UML:ModelElement.taggedValue>
								</UML:Attribute>
								<UML:Attribute name="Etableringsår" changeable="none" visibility="public" ownerScope="instance" targetScope="instance">
									<UML:Attribute.initialValue>
										<UML:Expression/>
									</UML:Attribute.initialValue>
									<UML:StructuralFeature.type>
										<UML:Classifier xmi.idref="EAID_BAFA5B86_CBF2_4baf_B443_CCD2BAB6CDF1"/>
									</UML:StructuralFeature.type>
									<UML:ModelElement.taggedValue>
										<UML:TaggedValue tag="description" value="Angir hvilket år vegstrekning ble etablert som TEN-T veg."/>
										<UML:TaggedValue tag="type" value="Tall"/>
										<UML:TaggedValue tag="derived" value="0"/>
										<UML:TaggedValue tag="containment" value="Not Specified"/>
										<UML:TaggedValue tag="length" value="4"/>
										<UML:TaggedValue tag="ordered" value="0"/>
										<UML:TaggedValue tag="precision" value="0"/>
										<UML:TaggedValue tag="scale" value="0"/>
										<UML:TaggedValue tag="static" value="0"/>
										<UML:TaggedValue tag="collection" value="false"/>
										<UML:TaggedValue tag="position" value="10"/>
										<UML:TaggedValue tag="lowerBound" value="0"/>
										<UML:TaggedValue tag="upperBound" value="1"/>
										<UML:TaggedValue tag="duplicates" value="0"/>
										<UML:TaggedValue tag="ea_guid" value="{6BD9EAA7-2B5A-4fae-9BB1-633F91E5EAA0}"/>
										<UML:TaggedValue tag="ea_localid" value="139098"/>
										<UML:TaggedValue tag="style" value="10949"/>
										<UML:TaggedValue tag="$ea_xref_property" value="$XREFPROP=$XID={F19A114F-7614-4bec-9D1E-2ADE872B7B96}$XID;$NAM=CustomProperties$NAM;$TYP=attribute property$TYP;$VIS=Public$VIS;$PAR=0$PAR;$DES=@PROP=@NAME=isID@ENDNAME;@TYPE=Boolean@ENDTYPE;@VALU=0@ENDVALU;@PRMT=@ENDPRMT;@ENDPROP;$DES;$CLT={6BD9EAA7-2B5A-4fae-9BB1-633F91E5EAA0}$CLT;$SUP=&lt;none&gt;$SUP;$ENDXREF;"/>
										<UML:TaggedValue tag="ID_EGENSKAPSTYPE" value="10949" xmi.id="EAID_5E9BF953_D2BA_4e1b_BF5D_64D237005DD8"/>
										<UML:TaggedValue tag="NAVN_EGENSKAPSTYPE" value="Etableringsår" xmi.id="EAID_7C3989F2_9A09_41c6_A33A_E3E48DB11495"/>
										<UML:TaggedValue tag="KORTN_EGENSKAPSTYPE" value="etablAar" xmi.id="EAID_BFBB02BA_697E_43c6_811C_7D8F0F9DEA70"/>
										<UML:TaggedValue tag="ANTALL_DESIMALER" value="0" xmi.id="EAID_5EE7EC4F_7D64_47da_804B_2ABD11815E13"/>
										<UML:TaggedValue tag="TOTAL_FELTLENGDE" value="4" xmi.id="EAID_F23FCACB_11F6_49c4_BB47_91AE0C58D0AA"/>
										<UML:TaggedValue tag="SOSINVDB_navn" value="Etableringsår_10949" xmi.id="EAID_B163D3B7_3E6A_4757_B45E_B513D7689395"/>
										<UML:TaggedValue tag="SOSI_navn" value="etableringsår" xmi.id="EAID_60D87641_A6D7_4b8e_AE26_695EF864B8E3"/>
										<UML:TaggedValue tag="Viktighet" value="Opsjonell" xmi.id="EAID_1E2B68C8_B38E_4708_B06E_2CA226593C7E"/>
									</UML:ModelElement.taggedValue>
								</UML:Attribute>
							</UML:Classifier.feature>
						</UML:Class>
						<UML:Association xmi.id="EAID_3F3E70E2_9171_45c9_BE04_B695EA360BAF" visibility="public" isRoot="false" isLeaf="false" isAbstract="false">
							<UML:ModelElement.taggedValue>
								<UML:TaggedValue tag="style" value="3"/>
								<UML:TaggedValue tag="ea_type" value="Aggregation"/>
								<UML:TaggedValue tag="direction" value="Bi-Directional"/>
								<UML:TaggedValue tag="linemode" value="3"/>
								<UML:TaggedValue tag="linecolor" value="0"/>
								<UML:TaggedValue tag="linewidth" value="0"/>
								<UML:TaggedValue tag="seqno" value="0"/>
								<UML:TaggedValue tag="subtype" value="Strong"/>
								<UML:TaggedValue tag="headStyle" value="0"/>
								<UML:TaggedValue tag="lineStyle" value="0"/>
								<UML:TaggedValue tag="ea_localid" value="18400"/>
								<UML:TaggedValue tag="ea_sourceName" value="Kommentar"/>
								<UML:TaggedValue tag="ea_targetName" value="TEN-T veg"/>
								<UML:TaggedValue tag="ea_sourceType" value="Class"/>
								<UML:TaggedValue tag="ea_targetType" value="Class"/>
								<UML:TaggedValue tag="ea_sourceID" value="28186"/>
								<UML:TaggedValue tag="ea_targetID" value="29200"/>
								<UML:TaggedValue tag="virtualInheritance" value="0"/>
								<UML:TaggedValue tag="lb" value="0..*"/>
								<UML:TaggedValue tag="lt" value="+Består av"/>
								<UML:TaggedValue tag="rb" value="0..1"/>
								<UML:TaggedValue tag="rt" value="+Er del av"/>
								<UML:TaggedValue tag="NVDB_ID" value="1886" xmi.id="EAID_5603B57F_6A0E_495b_842A_B714193C611A"/>
							</UML:ModelElement.taggedValue>
							<UML:Association.connection>
								<UML:AssociationEnd visibility="public" multiplicity="0..*" name="Består av" aggregation="none" isOrdered="false" isNavigable="true" type="EAID_C22D9383_866F_4fe6_837C_BA5FC0F2C41C">
									<UML:ModelElement.taggedValue>
										<UML:TaggedValue tag="sourcestyle" value="Owned=0;Navigable=Navigable;"/>
										<UML:TaggedValue tag="ea_end" value="source"/>
									</UML:ModelElement.taggedValue>
								</UML:AssociationEnd>
								<UML:AssociationEnd visibility="public" multiplicity="0..1" name="Er del av" aggregation="none" isOrdered="false" isNavigable="true" type="EAID_11EC4E2B_B58C_46c8_BECB_B180738A39C0">
									<UML:ModelElement.taggedValue>
										<UML:TaggedValue tag="deststyle" value="Owned=0;Navigable=Navigable;"/>
										<UML:TaggedValue tag="ea_end" value="target"/>
									</UML:ModelElement.taggedValue>
								</UML:AssociationEnd>
							</UML:Association.connection>
						</UML:Association>
						<UML:Association xmi.id="EAID_B4146D76_0EF2_4f81_A6AC_DA1A70C9840E" visibility="public" isRoot="false" isLeaf="false" isAbstract="false">
							<UML:ModelElement.taggedValue>
								<UML:TaggedValue tag="style" value="3"/>
								<UML:TaggedValue tag="ea_type" value="Aggregation"/>
								<UML:TaggedValue tag="direction" value="Bi-Directional"/>
								<UML:TaggedValue tag="linemode" value="3"/>
								<UML:TaggedValue tag="linecolor" value="0"/>
								<UML:TaggedValue tag="linewidth" value="0"/>
								<UML:TaggedValue tag="seqno" value="0"/>
								<UML:TaggedValue tag="subtype" value="Strong"/>
								<UML:TaggedValue tag="headStyle" value="0"/>
								<UML:TaggedValue tag="lineStyle" value="0"/>
								<UML:TaggedValue tag="ea_localid" value="18399"/>
								<UML:TaggedValue tag="ea_sourceName" value="Dokumentasjon"/>
								<UML:TaggedValue tag="ea_targetName" value="TEN-T veg"/>
								<UML:TaggedValue tag="ea_sourceType" value="Class"/>
								<UML:TaggedValue tag="ea_targetType" value="Class"/>
								<UML:TaggedValue tag="ea_sourceID" value="27651"/>
								<UML:TaggedValue tag="ea_targetID" value="29200"/>
								<UML:TaggedValue tag="virtualInheritance" value="0"/>
								<UML:TaggedValue tag="lb" value="0..*"/>
								<UML:TaggedValue tag="lt" value="+Består av"/>
								<UML:TaggedValue tag="rb" value="0..1"/>
								<UML:TaggedValue tag="rt" value="+Er del av"/>
								<UML:TaggedValue tag="NVDB_ID" value="1887" xmi.id="EAID_B34AD369_50FE_447e_BA87_820BA55C165C"/>
							</UML:ModelElement.taggedValue>
							<UML:Association.connection>
								<UML:AssociationEnd visibility="public" multiplicity="0..*" name="Består av" aggregation="none" isOrdered="false" isNavigable="true" type="EAID_8E1F2DD1_CBC2_477d_A711_455EA01A6041">
									<UML:ModelElement.taggedValue>
										<UML:TaggedValue tag="sourcestyle" value="Owned=0;Navigable=Navigable;"/>
										<UML:TaggedValue tag="ea_end" value="source"/>
									</UML:ModelElement.taggedValue>
								</UML:AssociationEnd>
								<UML:AssociationEnd visibility="public" multiplicity="0..1" name="Er del av" aggregation="none" isOrdered="false" isNavigable="true" type="EAID_11EC4E2B_B58C_46c8_BECB_B180738A39C0">
									<UML:ModelElement.taggedValue>
										<UML:TaggedValue tag="deststyle" value="Owned=0;Navigable=Navigable;"/>
										<UML:TaggedValue tag="ea_end" value="target"/>
									</UML:ModelElement.taggedValue>
								</UML:AssociationEnd>
							</UML:Association.connection>
						</UML:Association>
						<UML:Class name="CEDR ITS-nivå" xmi.id="EAID_354DF900_1385_484c_91A6_83B02506624C" visibility="public" namespace="EAPK_71E7E50B_00B3_41c4_8F29_D9DD21BE474C" isRoot="false" isLeaf="false" isAbstract="false" isActive="false">
							<UML:ModelElement.stereotype>
								<UML:Stereotype name="Tillatte verdier"/>
							</UML:ModelElement.stereotype>
							<UML:ModelElement.taggedValue>
								<UML:TaggedValue tag="documentation" value="Angir hvilket nivå vegstrekningen ligger på i forhold til ITS-systemer/ITS-styring. De ulike nivåene er definert av CEDR."/>
								<UML:TaggedValue tag="isSpecification" value="false"/>
								<UML:TaggedValue tag="ea_stype" value="Class"/>
								<UML:TaggedValue tag="ea_ntype" value="0"/>
								<UML:TaggedValue tag="version" value="2.27"/>
								<UML:TaggedValue tag="package" value="EAPK_71E7E50B_00B3_41c4_8F29_D9DD21BE474C"/>
								<UML:TaggedValue tag="date_created" value="2017-02-27 19:35:03"/>
								<UML:TaggedValue tag="date_modified" value="2021-12-29 18:22:15"/>
								<UML:TaggedValue tag="gentype" value="Java"/>
								<UML:TaggedValue tag="tagged" value="0"/>
								<UML:TaggedValue tag="package_name" value="TEN-T veg"/>
								<UML:TaggedValue tag="phase" value="1.0"/>
								<UML:TaggedValue tag="alias" value="10948"/>
								<UML:TaggedValue tag="author" value="Dakat"/>
								<UML:TaggedValue tag="complexity" value="1"/>
								<UML:TaggedValue tag="status" value="Implemented"/>
								<UML:TaggedValue tag="stereotype" value="Tillatte verdier"/>
								<UML:TaggedValue tag="tpos" value="2"/>
								<UML:TaggedValue tag="ea_localid" value="29201"/>
								<UML:TaggedValue tag="ea_eleType" value="element"/>
								<UML:TaggedValue tag="style" value="BackColor=-1;BorderColor=-1;BorderWidth=-1;FontColor=-1;VSwimLanes=1;HSwimLanes=1;BorderStyle=0;"/>
								<UML:TaggedValue tag="$ea_xref_property" value="$XREFPROP=$XID={4F5A6A33-B210-48bc-B776-1AC0D9AF1E71}$XID;$NAM=Stereotypes$NAM;$TYP=element property$TYP;$VIS=Public$VIS;$PAR=0$PAR;$DES=@STEREO;Name=Tillatte verdier;GUID={AE1C8A06-FFED-4f34-8B97-185A219BC442};@ENDSTEREO;$DES;$CLT={354DF900-1385-484c-91A6-83B02506624C}$CLT;$SUP=&lt;none&gt;$SUP;$ENDXREF;"/>
							</UML:ModelElement.taggedValue>
							<UML:Classifier.feature>
								<UML:Attribute name="Level 0" changeable="none" visibility="public" ownerScope="instance" targetScope="instance">
									<UML:Attribute.initialValue>
										<UML:Expression/>
									</UML:Attribute.initialValue>
									<UML:StructuralFeature.type>
										<UML:Classifier xmi.idref="eaxmiid0"/>
									</UML:StructuralFeature.type>
									<UML:ModelElement.taggedValue>
										<UML:TaggedValue tag="description" value="None"/>
										<UML:TaggedValue tag="derived" value="0"/>
										<UML:TaggedValue tag="containment" value="Not Specified"/>
										<UML:TaggedValue tag="length" value="0"/>
										<UML:TaggedValue tag="ordered" value="0"/>
										<UML:TaggedValue tag="precision" value="0"/>
										<UML:TaggedValue tag="scale" value="0"/>
										<UML:TaggedValue tag="static" value="0"/>
										<UML:TaggedValue tag="collection" value="false"/>
										<UML:TaggedValue tag="position" value="10"/>
										<UML:TaggedValue tag="lowerBound" value="1"/>
										<UML:TaggedValue tag="upperBound" value="1"/>
										<UML:TaggedValue tag="duplicates" value="0"/>
										<UML:TaggedValue tag="ea_guid" value="{78052B4F-B581-4d3c-B472-6102D30D4308}"/>
										<UML:TaggedValue tag="ea_localid" value="139099"/>
										<UML:TaggedValue tag="style" value="18290"/>
										<UML:TaggedValue tag="$ea_xref_property" value="$XREFPROP=$XID={D51BF007-2545-4a6f-9CEE-05924213AEB3}$XID;$NAM=CustomProperties$NAM;$TYP=attribute property$TYP;$VIS=Public$VIS;$PAR=0$PAR;$DES=@PROP=@NAME=isID@ENDNAME;@TYPE=Boolean@ENDTYPE;@VALU=0@ENDVALU;@PRMT=@ENDPRMT;@ENDPROP;$DES;$CLT={78052B4F-B581-4d3c-B472-6102D30D4308}$CLT;$SUP=&lt;none&gt;$SUP;$ENDXREF;"/>
										<UML:TaggedValue tag="ID_TILLATT_VERDI" value="18290" xmi.id="EAID_3F417C0F_31BB_406c_A96C_D6395338083F"/>
										<UML:TaggedValue tag="NAVN_TILLATT_VERDI" value="Level 0" xmi.id="EAID_BF84A60D_A827_4cc7_88AB_DB4F0C8DF458"/>
										<UML:TaggedValue tag="KORTN_TILLATT_VERDI" value="L0" xmi.id="EAID_46D8F6EF_C5A5_471c_BE6A_D1AB43F9EE30"/>
									</UML:ModelElement.taggedValue>
								</UML:Attribute>
								<UML:Attribute name="Level 1" changeable="none" visibility="public" ownerScope="instance" targetScope="instance">
									<UML:Attribute.initialValue>
										<UML:Expression/>
									</UML:Attribute.initialValue>
									<UML:StructuralFeature.type>
										<UML:Classifier xmi.idref="eaxmiid0"/>
									</UML:StructuralFeature.type>
									<UML:ModelElement.taggedValue>
										<UML:TaggedValue tag="description" value="Monitoring Systems"/>
										<UML:TaggedValue tag="derived" value="0"/>
										<UML:TaggedValue tag="containment" value="Not Specified"/>
										<UML:TaggedValue tag="length" value="0"/>
										<UML:TaggedValue tag="ordered" value="0"/>
										<UML:TaggedValue tag="precision" value="0"/>
										<UML:TaggedValue tag="scale" value="0"/>
										<UML:TaggedValue tag="static" value="0"/>
										<UML:TaggedValue tag="collection" value="false"/>
										<UML:TaggedValue tag="position" value="11"/>
										<UML:TaggedValue tag="lowerBound" value="1"/>
										<UML:TaggedValue tag="upperBound" value="1"/>
										<UML:TaggedValue tag="duplicates" value="0"/>
										<UML:TaggedValue tag="ea_guid" value="{FFCF8580-D711-4728-B539-5444BE22C2CA}"/>
										<UML:TaggedValue tag="ea_localid" value="139100"/>
										<UML:TaggedValue tag="style" value="18291"/>
										<UML:TaggedValue tag="$ea_xref_property" value="$XREFPROP=$XID={CCE9AD47-CD35-422d-BABF-01A7751F944A}$XID;$NAM=CustomProperties$NAM;$TYP=attribute property$TYP;$VIS=Public$VIS;$PAR=0$PAR;$DES=@PROP=@NAME=isID@ENDNAME;@TYPE=Boolean@ENDTYPE;@VALU=0@ENDVALU;@PRMT=@ENDPRMT;@ENDPROP;$DES;$CLT={FFCF8580-D711-4728-B539-5444BE22C2CA}$CLT;$SUP=&lt;none&gt;$SUP;$ENDXREF;"/>
										<UML:TaggedValue tag="ID_TILLATT_VERDI" value="18291" xmi.id="EAID_770ECB35_1EBB_4c08_91DE_B28698D8E76B"/>
										<UML:TaggedValue tag="NAVN_TILLATT_VERDI" value="Level 1" xmi.id="EAID_8A9471DE_97B1_4814_999A_895F0CC5BFED"/>
										<UML:TaggedValue tag="KORTN_TILLATT_VERDI" value="L1" xmi.id="EAID_F3C9AAE5_E553_45df_B1F2_2E157A996304"/>
									</UML:ModelElement.taggedValue>
								</UML:Attribute>
								<UML:Attribute name="Level 2" changeable="none" visibility="public" ownerScope="instance" targetScope="instance">
									<UML:Attribute.initialValue>
										<UML:Expression/>
									</UML:Attribute.initialValue>
									<UML:StructuralFeature.type>
										<UML:Classifier xmi.idref="eaxmiid0"/>
									</UML:StructuralFeature.type>
									<UML:ModelElement.taggedValue>
										<UML:TaggedValue tag="description" value="Level 1 + Travel information"/>
										<UML:TaggedValue tag="derived" value="0"/>
										<UML:TaggedValue tag="containment" value="Not Specified"/>
										<UML:TaggedValue tag="length" value="0"/>
										<UML:TaggedValue tag="ordered" value="0"/>
										<UML:TaggedValue tag="precision" value="0"/>
										<UML:TaggedValue tag="scale" value="0"/>
										<UML:TaggedValue tag="static" value="0"/>
										<UML:TaggedValue tag="collection" value="false"/>
										<UML:TaggedValue tag="position" value="12"/>
										<UML:TaggedValue tag="lowerBound" value="1"/>
										<UML:TaggedValue tag="upperBound" value="1"/>
										<UML:TaggedValue tag="duplicates" value="0"/>
										<UML:TaggedValue tag="ea_guid" value="{C99D46FD-BA5D-428e-A34B-4621A2B7D815}"/>
										<UML:TaggedValue tag="ea_localid" value="139101"/>
										<UML:TaggedValue tag="style" value="18292"/>
										<UML:TaggedValue tag="$ea_xref_property" value="$XREFPROP=$XID={7893DA0E-AD46-46b1-836E-00366F02C68C}$XID;$NAM=CustomProperties$NAM;$TYP=attribute property$TYP;$VIS=Public$VIS;$PAR=0$PAR;$DES=@PROP=@NAME=isID@ENDNAME;@TYPE=Boolean@ENDTYPE;@VALU=0@ENDVALU;@PRMT=@ENDPRMT;@ENDPROP;$DES;$CLT={C99D46FD-BA5D-428e-A34B-4621A2B7D815}$CLT;$SUP=&lt;none&gt;$SUP;$ENDXREF;"/>
										<UML:TaggedValue tag="ID_TILLATT_VERDI" value="18292" xmi.id="EAID_11EE3D72_07DC_4c7a_8254_100440A0269C"/>
										<UML:TaggedValue tag="NAVN_TILLATT_VERDI" value="Level 2" xmi.id="EAID_D64D675F_134F_49e0_8CAB_C42404873CD0"/>
										<UML:TaggedValue tag="KORTN_TILLATT_VERDI" value="L2" xmi.id="EAID_F35417E3_1CD7_4dce_BA61_AF3C27E032D6"/>
									</UML:ModelElement.taggedValue>
								</UML:Attribute>
								<UML:Attribute name="Level 3" changeable="none" visibility="public" ownerScope="instance" targetScope="instance">
									<UML:Attribute.initialValue>
										<UML:Expression/>
									</UML:Attribute.initialValue>
									<UML:StructuralFeature.type>
										<UML:Classifier xmi.idref="eaxmiid0"/>
									</UML:StructuralFeature.type>
									<UML:ModelElement.taggedValue>
										<UML:TaggedValue tag="description" value="Level 2 + Traffic Management"/>
										<UML:TaggedValue tag="derived" value="0"/>
										<UML:TaggedValue tag="containment" value="Not Specified"/>
										<UML:TaggedValue tag="length" value="0"/>
										<UML:TaggedValue tag="ordered" value="0"/>
										<UML:TaggedValue tag="precision" value="0"/>
										<UML:TaggedValue tag="scale" value="0"/>
										<UML:TaggedValue tag="static" value="0"/>
										<UML:TaggedValue tag="collection" value="false"/>
										<UML:TaggedValue tag="position" value="13"/>
										<UML:TaggedValue tag="lowerBound" value="1"/>
										<UML:TaggedValue tag="upperBound" value="1"/>
										<UML:TaggedValue tag="duplicates" value="0"/>
										<UML:TaggedValue tag="ea_guid" value="{61344F9D-DE0E-44ab-83DC-934C93C30571}"/>
										<UML:TaggedValue tag="ea_localid" value="139102"/>
										<UML:TaggedValue tag="style" value="18293"/>
										<UML:TaggedValue tag="$ea_xref_property" value="$XREFPROP=$XID={022C68B6-2F07-4759-9013-D17712B849D7}$XID;$NAM=CustomProperties$NAM;$TYP=attribute property$TYP;$VIS=Public$VIS;$PAR=0$PAR;$DES=@PROP=@NAME=isID@ENDNAME;@TYPE=Boolean@ENDTYPE;@VALU=0@ENDVALU;@PRMT=@ENDPRMT;@ENDPROP;$DES;$CLT={61344F9D-DE0E-44ab-83DC-934C93C30571}$CLT;$SUP=&lt;none&gt;$SUP;$ENDXREF;"/>
										<UML:TaggedValue tag="ID_TILLATT_VERDI" value="18293" xmi.id="EAID_E4F2E993_5E3E_485a_ACC0_963D5B94FFF4"/>
										<UML:TaggedValue tag="NAVN_TILLATT_VERDI" value="Level 3" xmi.id="EAID_05EE7EE1_7C25_4d28_86E2_B2A05FD1175B"/>
										<UML:TaggedValue tag="KORTN_TILLATT_VERDI" value="L3" xmi.id="EAID_E3621605_2136_4c52_BF8D_C5D7C8CC8DBA"/>
									</UML:ModelElement.taggedValue>
								</UML:Attribute>
								<UML:Attribute name="Level 4" changeable="none" visibility="public" ownerScope="instance" targetScope="instance">
									<UML:Attribute.initialValue>
										<UML:Expression/>
									</UML:Attribute.initialValue>
									<UML:StructuralFeature.type>
										<UML:Classifier xmi.idref="eaxmiid0"/>
									</UML:StructuralFeature.type>
									<UML:ModelElement.taggedValue>
										<UML:TaggedValue tag="description" value="Cooperative ITS (C-ITS)"/>
										<UML:TaggedValue tag="derived" value="0"/>
										<UML:TaggedValue tag="containment" value="Not Specified"/>
										<UML:TaggedValue tag="length" value="0"/>
										<UML:TaggedValue tag="ordered" value="0"/>
										<UML:TaggedValue tag="precision" value="0"/>
										<UML:TaggedValue tag="scale" value="0"/>
										<UML:TaggedValue tag="static" value="0"/>
										<UML:TaggedValue tag="collection" value="false"/>
										<UML:TaggedValue tag="position" value="14"/>
										<UML:TaggedValue tag="lowerBound" value="1"/>
										<UML:TaggedValue tag="upperBound" value="1"/>
										<UML:TaggedValue tag="duplicates" value="0"/>
										<UML:TaggedValue tag="ea_guid" value="{D1CAE389-B19D-40f6-85C4-A3001C27F674}"/>
										<UML:TaggedValue tag="ea_localid" value="139103"/>
										<UML:TaggedValue tag="style" value="18294"/>
										<UML:TaggedValue tag="$ea_xref_property" value="$XREFPROP=$XID={E27792D0-C455-4d48-B3AB-79964CEECE9E}$XID;$NAM=CustomProperties$NAM;$TYP=attribute property$TYP;$VIS=Public$VIS;$PAR=0$PAR;$DES=@PROP=@NAME=isID@ENDNAME;@TYPE=Boolean@ENDTYPE;@VALU=0@ENDVALU;@PRMT=@ENDPRMT;@ENDPROP;$DES;$CLT={D1CAE389-B19D-40f6-85C4-A3001C27F674}$CLT;$SUP=&lt;none&gt;$SUP;$ENDXREF;"/>
										<UML:TaggedValue tag="ID_TILLATT_VERDI" value="18294" xmi.id="EAID_3088F261_52A9_4f5e_A44F_FFA7686FFA76"/>
										<UML:TaggedValue tag="NAVN_TILLATT_VERDI" value="Level 4" xmi.id="EAID_1225CF3F_9266_4c50_BC52_B6C5C0AD9CC1"/>
										<UML:TaggedValue tag="KORTN_TILLATT_VERDI" value="L4" xmi.id="EAID_C4E6CF53_ED81_48e3_BCC2_1EEDED95E614"/>
									</UML:ModelElement.taggedValue>
								</UML:Attribute>
							</UML:Classifier.feature>
						</UML:Class>
						<UML:Class name="CEDR Vegtype" xmi.id="EAID_A7445D9B_7F4B_46b6_BFAF_18450AD35AA6" visibility="public" namespace="EAPK_71E7E50B_00B3_41c4_8F29_D9DD21BE474C" isRoot="false" isLeaf="false" isAbstract="false" isActive="false">
							<UML:ModelElement.stereotype>
								<UML:Stereotype name="Tillatte verdier"/>
							</UML:ModelElement.stereotype>
							<UML:ModelElement.taggedValue>
								<UML:TaggedValue tag="documentation" value="Angir hvilken vegtype det er tale om. Definisjoner av vegtyper i henhold til CEDR."/>
								<UML:TaggedValue tag="isSpecification" value="false"/>
								<UML:TaggedValue tag="ea_stype" value="Class"/>
								<UML:TaggedValue tag="ea_ntype" value="0"/>
								<UML:TaggedValue tag="version" value="2.27"/>
								<UML:TaggedValue tag="package" value="EAPK_71E7E50B_00B3_41c4_8F29_D9DD21BE474C"/>
								<UML:TaggedValue tag="date_created" value="2017-02-27 19:35:03"/>
								<UML:TaggedValue tag="date_modified" value="2021-12-29 18:22:15"/>
								<UML:TaggedValue tag="gentype" value="Java"/>
								<UML:TaggedValue tag="tagged" value="0"/>
								<UML:TaggedValue tag="package_name" value="TEN-T veg"/>
								<UML:TaggedValue tag="phase" value="1.0"/>
								<UML:TaggedValue tag="alias" value="10947"/>
								<UML:TaggedValue tag="author" value="Dakat"/>
								<UML:TaggedValue tag="complexity" value="1"/>
								<UML:TaggedValue tag="status" value="Implemented"/>
								<UML:TaggedValue tag="stereotype" value="Tillatte verdier"/>
								<UML:TaggedValue tag="tpos" value="3"/>
								<UML:TaggedValue tag="ea_localid" value="29202"/>
								<UML:TaggedValue tag="ea_eleType" value="element"/>
								<UML:TaggedValue tag="style" value="BackColor=-1;BorderColor=-1;BorderWidth=-1;FontColor=-1;VSwimLanes=1;HSwimLanes=1;BorderStyle=0;"/>
								<UML:TaggedValue tag="$ea_xref_property" value="$XREFPROP=$XID={7E844312-546A-490c-A970-62DF9D86516F}$XID;$NAM=Stereotypes$NAM;$TYP=element property$TYP;$VIS=Public$VIS;$PAR=0$PAR;$DES=@STEREO;Name=Tillatte verdier;GUID={AE1C8A06-FFED-4f34-8B97-185A219BC442};@ENDSTEREO;$DES;$CLT={A7445D9B-7F4B-46b6-BFAF-18450AD35AA6}$CLT;$SUP=&lt;none&gt;$SUP;$ENDXREF;"/>
							</UML:ModelElement.taggedValue>
							<UML:Classifier.feature>
								<UML:Attribute name="CEDR-motorveg" changeable="none" visibility="public" ownerScope="instance" targetScope="instance">
									<UML:Attribute.initialValue>
										<UML:Expression/>
									</UML:Attribute.initialValue>
									<UML:StructuralFeature.type>
										<UML:Classifier xmi.idref="eaxmiid0"/>
									</UML:StructuralFeature.type>
									<UML:ModelElement.taggedValue>
										<UML:TaggedValue tag="description" value="Veg kategoriseres som CEDR-motorveg"/>
										<UML:TaggedValue tag="derived" value="0"/>
										<UML:TaggedValue tag="containment" value="Not Specified"/>
										<UML:TaggedValue tag="length" value="0"/>
										<UML:TaggedValue tag="ordered" value="0"/>
										<UML:TaggedValue tag="precision" value="0"/>
										<UML:TaggedValue tag="scale" value="0"/>
										<UML:TaggedValue tag="static" value="0"/>
										<UML:TaggedValue tag="collection" value="false"/>
										<UML:TaggedValue tag="position" value="1"/>
										<UML:TaggedValue tag="lowerBound" value="1"/>
										<UML:TaggedValue tag="upperBound" value="1"/>
										<UML:TaggedValue tag="duplicates" value="0"/>
										<UML:TaggedValue tag="ea_guid" value="{B9F11711-4C8B-42be-826B-0359B0D93460}"/>
										<UML:TaggedValue tag="ea_localid" value="139104"/>
										<UML:TaggedValue tag="style" value="18295"/>
										<UML:TaggedValue tag="$ea_xref_property" value="$XREFPROP=$XID={9FDD320F-D98B-49f3-9FCC-73409E0F15F7}$XID;$NAM=CustomProperties$NAM;$TYP=attribute property$TYP;$VIS=Public$VIS;$PAR=0$PAR;$DES=@PROP=@NAME=isID@ENDNAME;@TYPE=Boolean@ENDTYPE;@VALU=0@ENDVALU;@PRMT=@ENDPRMT;@ENDPROP;$DES;$CLT={B9F11711-4C8B-42be-826B-0359B0D93460}$CLT;$SUP=&lt;none&gt;$SUP;$ENDXREF;"/>
										<UML:TaggedValue tag="ID_TILLATT_VERDI" value="18295" xmi.id="EAID_4DA2212F_1A02_4072_AF42_3FB7F8330570"/>
										<UML:TaggedValue tag="NAVN_TILLATT_VERDI" value="CEDR-motorveg" xmi.id="EAID_83162FEB_E48F_404c_93B0_4E326A22065F"/>
										<UML:TaggedValue tag="KORTN_TILLATT_VERDI" value="mv" xmi.id="EAID_D5FE03AB_C2A3_4cf9_A58D_08CB64597FF0"/>
									</UML:ModelElement.taggedValue>
								</UML:Attribute>
								<UML:Attribute name="Ikke CEDR Motorveg" changeable="none" visibility="public" ownerScope="instance" targetScope="instance">
									<UML:Attribute.initialValue>
										<UML:Expression/>
									</UML:Attribute.initialValue>
									<UML:StructuralFeature.type>
										<UML:Classifier xmi.idref="eaxmiid0"/>
									</UML:StructuralFeature.type>
									<UML:ModelElement.taggedValue>
										<UML:TaggedValue tag="description" value="Vegen kan ikke kategoriseres som CEDR-motorveg"/>
										<UML:TaggedValue tag="derived" value="0"/>
										<UML:TaggedValue tag="containment" value="Not Specified"/>
										<UML:TaggedValue tag="length" value="0"/>
										<UML:TaggedValue tag="ordered" value="0"/>
										<UML:TaggedValue tag="precision" value="0"/>
										<UML:TaggedValue tag="scale" value="0"/>
										<UML:TaggedValue tag="static" value="0"/>
										<UML:TaggedValue tag="collection" value="false"/>
										<UML:TaggedValue tag="position" value="2"/>
										<UML:TaggedValue tag="lowerBound" value="1"/>
										<UML:TaggedValue tag="upperBound" value="1"/>
										<UML:TaggedValue tag="duplicates" value="0"/>
										<UML:TaggedValue tag="ea_guid" value="{035273A2-5306-43ff-B4D0-3B56439C664F}"/>
										<UML:TaggedValue tag="ea_localid" value="139105"/>
										<UML:TaggedValue tag="style" value="18296"/>
										<UML:TaggedValue tag="$ea_xref_property" value="$XREFPROP=$XID={0C203680-207A-4336-996E-47D459AFA4B5}$XID;$NAM=CustomProperties$NAM;$TYP=attribute property$TYP;$VIS=Public$VIS;$PAR=0$PAR;$DES=@PROP=@NAME=isID@ENDNAME;@TYPE=Boolean@ENDTYPE;@VALU=0@ENDVALU;@PRMT=@ENDPRMT;@ENDPROP;$DES;$CLT={035273A2-5306-43ff-B4D0-3B56439C664F}$CLT;$SUP=&lt;none&gt;$SUP;$ENDXREF;"/>
										<UML:TaggedValue tag="ID_TILLATT_VERDI" value="18296" xmi.id="EAID_76FA24BF_12C9_4cb6_A831_2BBA56ECB8B5"/>
										<UML:TaggedValue tag="NAVN_TILLATT_VERDI" value="Ikke CEDR Motorveg" xmi.id="EAID_FA767A47_2F1B_4000_AE3B_047C87D165D0"/>
										<UML:TaggedValue tag="KORTN_TILLATT_VERDI" value="imv" xmi.id="EAID_104AA9B6_C1D5_49db_BBAA_DFF650845E70"/>
									</UML:ModelElement.taggedValue>
								</UML:Attribute>
							</UML:Classifier.feature>
						</UML:Class>
					</UML:Namespace.ownedElement>
				</UML:Package>
				<UML:DataType xmi.id="eaxmiid0" visibility="private" isRoot="false" isLeaf="false" isAbstract="false"/>
			</UML:Namespace.ownedElement>
		</UML:Model>
		<UML:TaggedValue tag="ID_VOBJ_TYPE" xmi.id="EAID_F1AFE618_AB44_4e00_9A52_79F3456884AE" value="826" modelElement="EAID_11EC4E2B_B58C_46c8_BECB_B180738A39C0"/>
		<UML:TaggedValue tag="KjorefeltRelevant" xmi.id="EAID_2ABAB405_5D2D_4295_B3E2_B6CC534F9096" value="0" modelElement="EAID_11EC4E2B_B58C_46c8_BECB_B180738A39C0"/>
		<UML:TaggedValue tag="KORTN_VOBJ_TYPE" xmi.id="EAID_461CE8C0_B51A_4494_878B_9161CEA80CE4" value="TenTveg" modelElement="EAID_11EC4E2B_B58C_46c8_BECB_B180738A39C0"/>
		<UML:TaggedValue tag="NAVN_VOBJ_TYPE" xmi.id="EAID_D1EDCBEF_A3AA_4804_A4A1_2016452D235B" value="TEN-T veg" modelElement="EAID_11EC4E2B_B58C_46c8_BECB_B180738A39C0"/>
		<UML:TaggedValue tag="SideposisjonRelevant" xmi.id="EAID_F8B0262C_68EB_4f47_A532_300313B7C38D" value="0" modelElement="EAID_11EC4E2B_B58C_46c8_BECB_B180738A39C0"/>
		<UML:TaggedValue tag="SOSI_navn" xmi.id="EAID_266B1820_540E_4838_BB29_9F609835BB5C" value="TEN_TVeg" modelElement="EAID_11EC4E2B_B58C_46c8_BECB_B180738A39C0"/>
		<UML:TaggedValue tag="SOSINVDB_navn" xmi.id="EAID_0540E803_D78B_4a53_B341_0AF1312E64A4" value="TEN-TVeg_826" modelElement="EAID_11EC4E2B_B58C_46c8_BECB_B180738A39C0"/>
		<UML:TaggedValue tag="Stedfesting" xmi.id="EAID_58B79B39_28CF_4616_B572_6001FFFB177C" value="strekning" modelElement="EAID_11EC4E2B_B58C_46c8_BECB_B180738A39C0"/>
		<UML:TaggedValue tag="ID_EGENSKAPSTYPE" xmi.id="EAID_57DA52D7_C058_4fa1_A341_B7B11F177DC5" value="10948" modelElement="EAID_354DF900_1385_484c_91A6_83B02506624C"/>
		<UML:TaggedValue tag="KORTN_EGENSKAPSTYPE" xmi.id="EAID_FAE5FCAE_17CC_419f_B5E6_C93E7C9E6F5E" value="ITSNiva" modelElement="EAID_354DF900_1385_484c_91A6_83B02506624C"/>
		<UML:TaggedValue tag="NAVN_EGENSKAPSTYPE" xmi.id="EAID_903632D6_22EC_4cc5_B1A9_5F63E5DBC24F" value="CEDR ITS-nivå" modelElement="EAID_354DF900_1385_484c_91A6_83B02506624C"/>
		<UML:TaggedValue tag="SOSI_datatype" xmi.id="EAID_6DDAE646_5DC5_415b_8F79_F137585F78B2" value="T" modelElement="EAID_354DF900_1385_484c_91A6_83B02506624C"/>
		<UML:TaggedValue tag="SOSI_navn" xmi.id="EAID_4FB9203F_2811_4a55_B724_84E872D668E8" value="DR_ITS_Nivå" modelElement="EAID_354DF900_1385_484c_91A6_83B02506624C"/>
		<UML:TaggedValue tag="TOTAL_FELTLENGDE" xmi.id="EAID_79B73DA0_94CF_4ba1_A5CB_7EA6362A1BCE" value="30" modelElement="EAID_354DF900_1385_484c_91A6_83B02506624C"/>
		<UML:TaggedValue tag="ID_EGENSKAPSTYPE" xmi.id="EAID_D7C7F108_83F5_4305_90DD_A83DA092EA7C" value="10947" modelElement="EAID_A7445D9B_7F4B_46b6_BFAF_18450AD35AA6"/>
		<UML:TaggedValue tag="KORTN_EGENSKAPSTYPE" xmi.id="EAID_2CF286AB_88E5_49c8_92E0_76062D4BD9AA" value="vegtype" modelElement="EAID_A7445D9B_7F4B_46b6_BFAF_18450AD35AA6"/>
		<UML:TaggedValue tag="NAVN_EGENSKAPSTYPE" xmi.id="EAID_02A75F13_9503_4fc9_9D5E_7DD04DA33EB8" value="CEDR Vegtype" modelElement="EAID_A7445D9B_7F4B_46b6_BFAF_18450AD35AA6"/>
		<UML:TaggedValue tag="SOSI_datatype" xmi.id="EAID_8739A6B4_21F1_4f7d_B919_97F9F69D4F42" value="T" modelElement="EAID_A7445D9B_7F4B_46b6_BFAF_18450AD35AA6"/>
		<UML:TaggedValue tag="SOSI_navn" xmi.id="EAID_FC9878D2_F298_4cdd_85E8_69FC91A7F627" value="CEDRVegtype" modelElement="EAID_A7445D9B_7F4B_46b6_BFAF_18450AD35AA6"/>
		<UML:TaggedValue tag="TOTAL_FELTLENGDE" xmi.id="EAID_A019A168_958F_485f_99FF_4540C9B3A77A" value="20" modelElement="EAID_A7445D9B_7F4B_46b6_BFAF_18450AD35AA6"/>
		<UML:Diagram name="TEN-T veg Betingelser" xmi.id="EAID_6B25792C_7C27_4942_B0D3_A9701746ECF5" diagramType="ClassDiagram" owner="EAPK_71E7E50B_00B3_41c4_8F29_D9DD21BE474C" toolName="Enterprise Architect 2.5">
			<UML:ModelElement.taggedValue>
				<UML:TaggedValue tag="version" value="2.27"/>
				<UML:TaggedValue tag="author" value="Dakat"/>
				<UML:TaggedValue tag="created_date" value="2017-02-27 21:35:38"/>
				<UML:TaggedValue tag="modified_date" value="2017-02-27 21:35:39"/>
				<UML:TaggedValue tag="package" value="EAPK_71E7E50B_00B3_41c4_8F29_D9DD21BE474C"/>
				<UML:TaggedValue tag="type" value="Logical"/>
				<UML:TaggedValue tag="swimlanes" value="locked=false;orientation=0;width=0;inbar=false;names=false;color=-1;bold=false;fcol=0;tcol=-1;ofCol=-1;ufCol=-1;hl=0;ufh=0;hh=0;cls=0;bw=0;hli=0;bro=0;SwimlaneFont=lfh:-10,lfw:0,lfi:0,lfu:0,lfs:0,lfface:Calibri,lfe:0,lfo:0,lfchar:1,lfop:0,lfcp:0,lfq:0,lfpf=0,lfWidth=0;"/>
				<UML:TaggedValue tag="matrixitems" value="locked=false;matrixactive=false;swimlanesactive=true;kanbanactive=false;width=1;clrLine=0;"/>
				<UML:TaggedValue tag="tpos" value="0"/>
				<UML:TaggedValue tag="ea_localid" value="7308"/>
				<UML:TaggedValue tag="EAStyle" value="ShowPrivate=1;ShowProtected=1;ShowPublic=1;HideRelationships=0;Locked=0;Border=1;HighlightForeign=0;PackageContents=1;SequenceNotes=0;ScalePrintImage=0;PPgs.cx=1;PPgs.cy=1;DocSize.cx=800;DocSize.cy=1100;ShowDetails=0;Orientation=P;Zoom=100;ShowTags=0;OpParams=1;VisibleAttributeDetail=0;ShowOpRetType=1;ShowIcons=1;CollabNums=0;HideProps=0;ShowReqs=0;ShowCons=0;PaperSize=9;HideParents=0;UseAlias=0;HideAtts=0;HideOps=0;HideStereo=0;HideElemStereo=0;ShowTests=0;ShowMaint=0;ConnectorNotation=UML 2.1;ExplicitNavigability=0;ShowShape=1;AllDockable=0;AdvancedElementProps=1;AdvancedFeatureProps=1;AdvancedConnectorProps=1;m_bElementClassifier=1;SPT=1;ShowNotes=0;SuppressBrackets=0;SuppConnectorLabels=0;PrintPageHeadFoot=0;ShowAsList=0;"/>
				<UML:TaggedValue tag="styleex" value="SaveTag=4D9CBAFF;ExcludeRTF=0;DocAll=0;HideQuals=0;AttPkg=1;ShowTests=0;ShowMaint=0;Layout=l=20:c=20:d=0:cr=0:la=0:i=0:it=4:a=0:;SuppressFOC=1;MatrixActive=0;SwimlanesActive=1;KanbanActive=0;MatrixLineWidth=1;MatrixLineClr=0;MatrixLocked=0;TConnectorNotation=UML 2.1;TExplicitNavigability=0;AdvancedElementProps=1;AdvancedFeatureProps=1;AdvancedConnectorProps=1;m_bElementClassifier=1;SPT=1;MDGDgm=;STBLDgm=;ShowNotes=0;VisibleAttributeDetail=0;ShowOpRetType=1;SuppressBrackets=0;SuppConnectorLabels=0;PrintPageHeadFoot=0;ShowAsList=0;SuppressedCompartments=;Theme=:119;"/>
			</UML:ModelElement.taggedValue>
			<UML:Diagram.element>
				<UML:DiagramElement geometry="Left=20;Top=20;Right=228;Bottom=131;" subject="EAID_11EC4E2B_B58C_46c8_BECB_B180738A39C0" seqno="1" style="Constraint=1;DUID=75CB1F5A;"/>
			</UML:Diagram.element>
		</UML:Diagram>
		<UML:Diagram name="TEN-T veg Tillatte verdier" xmi.id="EAID_F36D58C8_B2F4_4477_9B49_3A97BD39DBCE" diagramType="ClassDiagram" owner="EAPK_71E7E50B_00B3_41c4_8F29_D9DD21BE474C" toolName="Enterprise Architect 2.5">
			<UML:ModelElement.taggedValue>
				<UML:TaggedValue tag="version" value="2.27"/>
				<UML:TaggedValue tag="author" value="Dakat"/>
				<UML:TaggedValue tag="created_date" value="2017-02-27 21:35:39"/>
				<UML:TaggedValue tag="modified_date" value="2017-02-27 21:35:40"/>
				<UML:TaggedValue tag="package" value="EAPK_71E7E50B_00B3_41c4_8F29_D9DD21BE474C"/>
				<UML:TaggedValue tag="type" value="Logical"/>
				<UML:TaggedValue tag="swimlanes" value="locked=false;orientation=0;width=0;inbar=false;names=false;color=-1;bold=false;fcol=0;tcol=-1;ofCol=-1;ufCol=-1;hl=0;ufh=0;hh=0;cls=0;bw=0;hli=0;bro=0;SwimlaneFont=lfh:-10,lfw:0,lfi:0,lfu:0,lfs:0,lfface:Calibri,lfe:0,lfo:0,lfchar:1,lfop:0,lfcp:0,lfq:0,lfpf=0,lfWidth=0;"/>
				<UML:TaggedValue tag="matrixitems" value="locked=false;matrixactive=false;swimlanesactive=true;kanbanactive=false;width=1;clrLine=0;"/>
				<UML:TaggedValue tag="tpos" value="0"/>
				<UML:TaggedValue tag="ea_localid" value="7309"/>
				<UML:TaggedValue tag="EAStyle" value="ShowPrivate=1;ShowProtected=1;ShowPublic=1;HideRelationships=0;Locked=0;Border=1;HighlightForeign=0;PackageContents=1;SequenceNotes=0;ScalePrintImage=0;PPgs.cx=1;PPgs.cy=1;DocSize.cx=800;DocSize.cy=1100;ShowDetails=0;Orientation=P;Zoom=100;ShowTags=0;OpParams=1;VisibleAttributeDetail=0;ShowOpRetType=1;ShowIcons=1;CollabNums=0;HideProps=0;ShowReqs=0;ShowCons=0;PaperSize=9;HideParents=0;UseAlias=0;HideAtts=0;HideOps=0;HideStereo=0;HideElemStereo=0;ShowTests=0;ShowMaint=0;ConnectorNotation=UML 2.1;ExplicitNavigability=0;ShowShape=1;AllDockable=0;AdvancedElementProps=1;AdvancedFeatureProps=1;AdvancedConnectorProps=1;m_bElementClassifier=1;SPT=1;ShowNotes=0;SuppressBrackets=0;SuppConnectorLabels=0;PrintPageHeadFoot=0;ShowAsList=0;"/>
				<UML:TaggedValue tag="styleex" value="SaveTag=1AA614C4;ExcludeRTF=0;DocAll=0;HideQuals=0;AttPkg=1;ShowTests=0;ShowMaint=0;Layout=l=20:c=20:d=0:cr=0:la=0:i=0:it=4:a=0:;SuppressFOC=1;MatrixActive=0;SwimlanesActive=1;KanbanActive=0;MatrixLineWidth=1;MatrixLineClr=0;MatrixLocked=0;TConnectorNotation=UML 2.1;TExplicitNavigability=0;AdvancedElementProps=1;AdvancedFeatureProps=1;AdvancedConnectorProps=1;m_bElementClassifier=1;SPT=1;MDGDgm=;STBLDgm=;ShowNotes=0;VisibleAttributeDetail=0;ShowOpRetType=1;SuppressBrackets=0;SuppConnectorLabels=0;PrintPageHeadFoot=0;ShowAsList=0;SuppressedCompartments=;Theme=:119;"/>
			</UML:ModelElement.taggedValue>
			<UML:Diagram.element>
				<UML:DiagramElement geometry="Left=378;Top=20;Right=468;Bottom=131;" subject="EAID_354DF900_1385_484c_91A6_83B02506624C" seqno="1" style="DUID=3C9CA330;"/>
				<UML:DiagramElement geometry="Left=248;Top=20;Right=358;Bottom=90;" subject="EAID_A7445D9B_7F4B_46b6_BFAF_18450AD35AA6" seqno="2" style="DUID=F2A0D9C3;"/>
				<UML:DiagramElement geometry="Left=20;Top=20;Right=228;Bottom=131;" subject="EAID_11EC4E2B_B58C_46c8_BECB_B180738A39C0" seqno="3" style="DUID=98264995;"/>
			</UML:Diagram.element>
		</UML:Diagram>
		<UML:Diagram name="TEN-T veg Assosiasjoner" xmi.id="EAID_B323D94C_C7AC_4355_A647_B958B248588A" diagramType="ClassDiagram" owner="EAPK_71E7E50B_00B3_41c4_8F29_D9DD21BE474C" toolName="Enterprise Architect 2.5">
			<UML:ModelElement.taggedValue>
				<UML:TaggedValue tag="version" value="2.27"/>
				<UML:TaggedValue tag="author" value="Dakat"/>
				<UML:TaggedValue tag="created_date" value="2017-02-27 21:35:40"/>
				<UML:TaggedValue tag="modified_date" value="2017-03-04 15:31:40"/>
				<UML:TaggedValue tag="package" value="EAPK_71E7E50B_00B3_41c4_8F29_D9DD21BE474C"/>
				<UML:TaggedValue tag="type" value="Logical"/>
				<UML:TaggedValue tag="swimlanes" value="locked=false;orientation=0;width=0;inbar=false;names=false;color=-1;bold=false;fcol=0;tcol=-1;ofCol=-1;ufCol=-1;hl=0;ufh=0;hh=0;cls=0;bw=0;hli=0;bro=0;SwimlaneFont=lfh:-10,lfw:0,lfi:0,lfu:0,lfs:0,lfface:Calibri,lfe:0,lfo:0,lfchar:1,lfop:0,lfcp:0,lfq:0,lfpf=0,lfWidth=0;"/>
				<UML:TaggedValue tag="matrixitems" value="locked=false;matrixactive=false;swimlanesactive=true;kanbanactive=false;width=1;clrLine=0;"/>
				<UML:TaggedValue tag="tpos" value="0"/>
				<UML:TaggedValue tag="ea_localid" value="7310"/>
				<UML:TaggedValue tag="EAStyle" value="ShowPrivate=1;ShowProtected=1;ShowPublic=1;HideRelationships=0;Locked=0;Border=1;HighlightForeign=0;PackageContents=1;SequenceNotes=0;ScalePrintImage=0;PPgs.cx=1;PPgs.cy=1;DocSize.cx=800;DocSize.cy=1100;ShowDetails=0;Orientation=P;Zoom=100;ShowTags=0;OpParams=1;VisibleAttributeDetail=0;ShowOpRetType=1;ShowIcons=1;CollabNums=0;HideProps=0;ShowReqs=0;ShowCons=0;PaperSize=9;HideParents=0;UseAlias=0;HideAtts=0;HideOps=0;HideStereo=0;HideElemStereo=0;ShowTests=0;ShowMaint=0;ConnectorNotation=UML 2.1;ExplicitNavigability=0;ShowShape=1;AllDockable=0;AdvancedElementProps=1;AdvancedFeatureProps=1;AdvancedConnectorProps=1;m_bElementClassifier=1;SPT=1;ShowNotes=0;SuppressBrackets=0;SuppConnectorLabels=0;PrintPageHeadFoot=0;ShowAsList=0;"/>
				<UML:TaggedValue tag="styleex" value="SaveTag=B3668C9A;ExcludeRTF=0;DocAll=0;HideQuals=0;AttPkg=1;ShowTests=0;ShowMaint=0;Layout=l=20:c=20:d=0:cr=0:la=0:i=0:it=4:a=0:;SuppressFOC=1;MatrixActive=0;SwimlanesActive=1;KanbanActive=0;MatrixLineWidth=1;MatrixLineClr=0;MatrixLocked=0;TConnectorNotation=UML 2.1;TExplicitNavigability=0;AdvancedElementProps=1;AdvancedFeatureProps=1;AdvancedConnectorProps=1;m_bElementClassifier=1;SPT=1;MDGDgm=;STBLDgm=;ShowNotes=0;VisibleAttributeDetail=0;ShowOpRetType=1;SuppressBrackets=0;SuppConnectorLabels=0;PrintPageHeadFoot=0;ShowAsList=0;SuppressedCompartments=;Theme=:119;"/>
			</UML:ModelElement.taggedValue>
			<UML:Diagram.element>
				<UML:DiagramElement geometry="Left=156;Top=25;Right=364;Bottom=136;" subject="EAID_11EC4E2B_B58C_46c8_BECB_B180738A39C0" seqno="1" style="DUID=2B5243A3;"/>
				<UML:DiagramElement geometry="Left=300;Top=220;Right=500;Bottom=290;" subject="EAID_8E1F2DD1_CBC2_477d_A711_455EA01A6041" seqno="2" style="AttPub=0;DUID=07D745CA;"/>
				<UML:DiagramElement geometry="Left=40;Top=220;Right=240;Bottom=290;" subject="EAID_C22D9383_866F_4fe6_837C_BA5FC0F2C41C" seqno="3" style="AttPub=0;DUID=57681F25;"/>
				<UML:DiagramElement geometry="SX=0;SY=0;EX=0;EY=0;EDGE=1;$LLB=CX=16:CY=13:OX=0:OY=0:HDN=0:BLD=0:ITA=0:UND=0:CLR=-1:ALN=0:DIR=0:ROT=0;LLT=CX=42:CY=13:OX=0:OY=0:HDN=0:BLD=0:ITA=0:UND=0:CLR=-1:ALN=0:DIR=0:ROT=0;LMT=;LMB=;LRT=CX=39:CY=13:OX=0:OY=0:HDN=0:BLD=0:ITA=0:UND=0:CLR=-1:ALN=0:DIR=0:ROT=0;LRB=CX=16:CY=13:OX=0:OY=0:HDN=0:BLD=0:ITA=0:UND=0:CLR=-1:ALN=0:DIR=0:ROT=0;IRHS=;ILHS=;Path=;" subject="EAID_3F3E70E2_9171_45c9_BE04_B695EA360BAF" style="Mode=2;EOID=2B5243A3;SOID=57681F25;Color=-1;LWidth=0;Hidden=0;"/>
				<UML:DiagramElement geometry="SX=0;SY=0;EX=0;EY=0;EDGE=1;$LLB=CX=16:CY=13:OX=0:OY=0:HDN=0:BLD=0:ITA=0:UND=0:CLR=-1:ALN=0:DIR=0:ROT=0;LLT=CX=42:CY=13:OX=0:OY=0:HDN=0:BLD=0:ITA=0:UND=0:CLR=-1:ALN=0:DIR=0:ROT=0;LMT=;LMB=;LRT=CX=39:CY=13:OX=0:OY=0:HDN=0:BLD=0:ITA=0:UND=0:CLR=-1:ALN=0:DIR=0:ROT=0;LRB=CX=16:CY=13:OX=0:OY=0:HDN=0:BLD=0:ITA=0:UND=0:CLR=-1:ALN=0:DIR=0:ROT=0;IRHS=;ILHS=;Path=;" subject="EAID_B4146D76_0EF2_4f81_A6AC_DA1A70C9840E" style="Mode=2;EOID=2B5243A3;SOID=07D745CA;Color=-1;LWidth=0;Hidden=0;"/>
				<UML:DiagramElement geometry="EDGE=0;$LLB=;LLT=;LMT=;LMB=;LRT=;LRB=;IRHS=;ILHS=;Path=;" subject="EAID_E7AE146A_8274_4b31_9E85_ACD9F756E6E6" style="Mode=3;EOID=57681F25;SOID=07D745CA;Color=-1;LWidth=0;Hidden=1;"/>
			</UML:Diagram.element>
		</UML:Diagram>
	</XMI.content>
	<XMI.difference/>
	<XMI.extensions xmi.extender="Enterprise Architect 2.5">
		<EAStub xmi.id="EAID_C22D9383_866F_4fe6_837C_BA5FC0F2C41C" name="Kommentar" UMLType="Class"/>
		<EAStub xmi.id="EAID_8E1F2DD1_CBC2_477d_A711_455EA01A6041" name="Dokumentasjon" UMLType="Class"/>
		<EAStub xmi.id="EAID_968D5712_8BD7_4710_BA39_A16179F74C46" name="Tekst" UMLType="Class"/>
		<EAStub xmi.id="EAID_6F0E67D6_1534_467f_89B2_D454FE1774C3" name="FlerverdiAttributt, Tekst" UMLType="Class"/>
		<EAStub xmi.id="EAID_BAFA5B86_CBF2_4baf_B443_CCD2BAB6CDF1" name="Tall" UMLType="Class"/>
	</XMI.extensions>
</XMI>
